sklekmeans/__init__.py
sklekmeans/_ekmeans.py
sklekmeans/_ssekmeans.py
sklekmeans-0.2.1.dist-info/licenses/LICENSE
sklekmeans-0.2.1.dist-info/METADATA
sklekmeans-0.2.1.dist-info/WHEEL
sklekmeans-0.2.1.dist-info/top_level.txt
sklekmeans-0.2.1.dist-info/RECORD
